Quantsbin-1.0.2.dist-info/METADATA
Quantsbin-1.0.2.dist-info/RECORD
Quantsbin-1.0.2.dist-info/WHEEL
Quantsbin-1.0.2.dist-info/top_level.txt
quantsbin/__init__.py
quantsbin/derivativepricing/__init__.py
quantsbin/derivativepricing/engineconfig.py
quantsbin/derivativepricing/helperfn.py
quantsbin/derivativepricing/instruments.py
quantsbin/derivativepricing/namesnmapper.py
quantsbin/derivativepricing/numericalgreeks.py
quantsbin/derivativepricing/optionstrategies.py
quantsbin/derivativepricing/plotting.py
quantsbin/derivativepricing/pricingmodels.py
quantsbin/montecarlo/__init__.py
quantsbin/montecarlo/namesnmapper.py
quantsbin/montecarlo/stimulations.py
