Metadata-Version: 2.1
Name: Quantsbin
Version: 1.0.2
Summary: Quantitative Finance Tools
Home-page: https://github.com/quantsbin/Quantsbin
Author: Quantsbin
Author-email: contactus@quantsbin.com
License: MIT
Platform: UNKNOWN
